mathfuncs_parse.cp311-win_amd64.pyd
mathfuncs_parse-1.1.4.dist-info/METADATA
mathfuncs_parse-1.1.4.dist-info/WHEEL
mathfuncs_parse-1.1.4.dist-info/top_level.txt
mathfuncs_parse-1.1.4.dist-info/RECORD
