Metadata-Version: 2.1
Name: mathfuncs-parse
Version: 1.1.4
Summary: A small module for parsing and evaluating expressions of any number of variables
Author: David Laeer
Author-email: davidlaeer@gmail.com
